oc_sql_helpers/__init__.py
oc_sql_helpers/normalizer.py
oc_sql_helpers/str_decoder.py
oc_sql_helpers/wrapper.py
oc_sql_helpers-1.0.3.dist-info/LICENSE
oc_sql_helpers-1.0.3.dist-info/METADATA
oc_sql_helpers-1.0.3.dist-info/WHEEL
oc_sql_helpers-1.0.3.dist-info/top_level.txt
oc_sql_helpers-1.0.3.dist-info/RECORD
