Metadata-Version: 2.1
Name: oc-sql-helpers
Version: 1.0.3
Summary: Helper classes for PL/SQL source code files
License: LGPLv2
Requires-Python: >=3.6
License-File: LICENSE
Requires-Dist: chardet (>=2.3.0)
